{
  "version": "69d4b73d",
  "entry": {
    "module": "/build/entry.client-MKQOAIZ2.js",
    "imports": [
      "/build/_shared/chunk-M3CTSPVS.js",
      "/build/_shared/chunk-E7VMOUYL.js"
    ]
  },
  "routes": {
    "root": {
      "id": "root",
      "path": "",
      "module": "/build/root-5WDYOEBM.js",
      "hasAction": false,
      "hasLoader": false,
      "hasCatchBoundary": false,
      "hasErrorBoundary": false
    },
    "routes/$slug": {
      "id": "routes/$slug",
      "parentId": "root",
      "path": ":slug",
      "module": "/build/routes/$slug-2DP6ZMUL.js",
      "imports": [
        "/build/_shared/chunk-SLNHJ22I.js"
      ],
      "hasAction": false,
      "hasLoader": true,
      "hasCatchBoundary": false,
      "hasErrorBoundary": false
    },
    "routes/about": {
      "id": "routes/about",
      "parentId": "root",
      "path": "about",
      "module": "/build/routes/about-PMXXDA3N.js",
      "hasAction": false,
      "hasLoader": false,
      "hasCatchBoundary": false,
      "hasErrorBoundary": false
    },
    "routes/index": {
      "id": "routes/index",
      "parentId": "root",
      "index": true,
      "module": "/build/routes/index-FFKSO5IK.js",
      "imports": [
        "/build/_shared/chunk-SLNHJ22I.js"
      ],
      "hasAction": false,
      "hasLoader": true,
      "hasCatchBoundary": false,
      "hasErrorBoundary": false
    }
  },
  "url": "/build/manifest-69D4B73D.js"
}